pogo_migrate/__init__.py
pogo_migrate/cli.py
pogo_migrate/config.py
pogo_migrate/context.py
pogo_migrate/exceptions.py
pogo_migrate/migrate.py
pogo_migrate/migration.py
pogo_migrate/py.typed
pogo_migrate/sql.py
pogo_migrate/squash.py
pogo_migrate/testing.py
pogo_migrate/util.py
pogo_migrate/yoyo.py
pogo_migrate-0.4.1.dist-info/METADATA
pogo_migrate-0.4.1.dist-info/WHEEL
pogo_migrate-0.4.1.dist-info/entry_points.txt
pogo_migrate-0.4.1.dist-info/RECORD
