Metadata-Version: 2.4
Name: pogo-migrate
Version: 0.4.1
Summary: Database migration tool for asyncpg
Project-URL: homepage, https://github.com/NRWLDev/pogo-migrate
Project-URL: documentation, https://nrwldev.github.io/pogo-migrate/
Author-email: Daniel Edgecombe <daniel@nrwl.co>
Maintainer-email: Daniel Edgecombe <daniel@nrwl.co>
License-Expression: Apache-2.0
Keywords: asyncpg,database,migrate,migrations,yoyo
Classifier: Development Status :: 4 - Beta
Classifier: Environment :: Console
Classifier: Intended Audience :: Developers
Classifier: License :: OSI Approved :: Apache Software License
Classifier: Operating System :: OS Independent
Classifier: Programming Language :: Python
Classifier: Programming Language :: Python :: 3
Classifier: Programming Language :: Python :: 3 :: Only
Classifier: Programming Language :: Python :: 3.10
Classifier: Programming Language :: Python :: 3.11
Classifier: Programming Language :: Python :: 3.12
Classifier: Programming Language :: Python :: 3.13
Classifier: Topic :: Database
Classifier: Topic :: Software Development
Requires-Python: <3.14,>=3.10
Requires-Dist: pogo-core>=0.1.2
Requires-Dist: python-dotenv>=1.0.0
Requires-Dist: rtoml>=0.10
Requires-Dist: sqlglot>=25.19
Requires-Dist: sqlparse>=0.5.2
Requires-Dist: tabulate>=0.9.0
Requires-Dist: typer-slim>=0
Provides-Extra: dev
Requires-Dist: asyncpg>=0.31.0; extra == 'dev'
Requires-Dist: changelog-gen>=0.13; extra == 'dev'
Requires-Dist: nest-asyncio>=1.6.0; extra == 'dev'
Requires-Dist: pre-commit>=3.7.1; extra == 'dev'
Requires-Dist: pytest-asyncio>=1.3.0; extra == 'dev'
Requires-Dist: pytest-cov>=7.0.0; extra == 'dev'
Requires-Dist: pytest-env>=0.8.1; extra == 'dev'
Requires-Dist: pytest-random-order>=1.2.0; extra == 'dev'
Requires-Dist: pytest>=9.0.2; extra == 'dev'
Requires-Dist: ruff>=0.14.10; extra == 'dev'
